setup.py
odoo/addons/helpdesk_somconnexio/CHANGELOG.md
odoo/addons/helpdesk_somconnexio/README.rst
odoo/addons/helpdesk_somconnexio/__init__.py
odoo/addons/helpdesk_somconnexio/__manifest__.py
odoo/addons/helpdesk_somconnexio/i18n/ca_ES.po
odoo/addons/helpdesk_somconnexio/i18n/es.po
odoo/addons/helpdesk_somconnexio/i18n/helpdesk_somconnexio.pot
odoo/addons/helpdesk_somconnexio/models/__init__.py
odoo/addons/helpdesk_somconnexio/models/helpdesk_ticket.py
odoo/addons/helpdesk_somconnexio/models/helpdesk_ticket_primary_tag.py
odoo/addons/helpdesk_somconnexio/models/helpdesk_ticket_secondary_tag.py
odoo/addons/helpdesk_somconnexio/security/ir.model.access.csv
odoo/addons/helpdesk_somconnexio/views/helpdesk_ticket_menu.xml
odoo/addons/helpdesk_somconnexio/views/helpdesk_ticket_view.xml
odoo/addons/helpdesk_somconnexio/wizards/__init__.py
odoo/addons/helpdesk_somconnexio/wizards/mail_compose_message.py
odoo/addons/helpdesk_somconnexio/wizards/mail_compose_message_view.xml
odoo_addon_helpdesk_somconnexio.egg-info/PKG-INFO
odoo_addon_helpdesk_somconnexio.egg-info/SOURCES.txt
odoo_addon_helpdesk_somconnexio.egg-info/dependency_links.txt
odoo_addon_helpdesk_somconnexio.egg-info/not-zip-safe
odoo_addon_helpdesk_somconnexio.egg-info/requires.txt
odoo_addon_helpdesk_somconnexio.egg-info/top_level.txt