Metadata-Version: 1.2
Name: odoo-addon-helpdesk-somconnexio
Version: 16.0.1.0.0
Summary: Odoo Helpdesk customizations for Som Connexió
Home-page: https://coopdevs.org
Author: Som It Cooperatiu SCCL, Som Connexió SCCL
License: AGPL-3
Platform: UNKNOWN
Classifier: Programming Language :: Python
Classifier: Framework :: Odoo
Classifier: Framework :: Odoo :: 16.0
Classifier: License :: OSI Approved :: GNU Affero General Public License v3
Requires-Python: >=3.10
